{"cameraMode":{"drawMode":0,"name":"Shaded","section":"Shading Mode"},"sceneLighting":false,"audioPlay":false,"sceneViewState":{"showFog":true,"showMaterialUpdate":false,"showSkybox":false,"showFlares":true,"showImageEffects":true,"showParticleSystems":true},"in2DMode":false,"pivot":{"x":0.02499997615814209,"y":1.0609030723571778,"z":1.304246187210083},"rotation":{"x":-0.18670816719532014,"y":0.006480562500655651,"z":-0.0012363999849185348,"w":-0.9824187755584717},"size":1.483551025390625,"orthographic":false}